shiertier_modelscope/__init__.py
shiertier_modelscope/modelscope.py
shiertier_modelscope-0.0.3.dist-info/LICENSE
shiertier_modelscope-0.0.3.dist-info/METADATA
shiertier_modelscope-0.0.3.dist-info/WHEEL
shiertier_modelscope-0.0.3.dist-info/top_level.txt
shiertier_modelscope-0.0.3.dist-info/RECORD
